flav_module/__init__.py
flav_module/helloworld.py
flav_module-0.16.dist-info/entry_points.txt
flav_module-0.16.dist-info/LICENSE
flav_module-0.16.dist-info/WHEEL
flav_module-0.16.dist-info/METADATA
flav_module-0.16.dist-info/RECORD
